quickhooks/__init__.py
quickhooks/__main__.py
quickhooks/config.py
quickhooks/dev.py
quickhooks/exceptions.py
quickhooks/executor.py
quickhooks/features.py
quickhooks/models.py
quickhooks/py.typed
quickhooks/runner.py
quickhooks/agent_analysis/__init__.py
quickhooks/agent_analysis/agent_discovery.py
quickhooks/agent_analysis/analyzer.py
quickhooks/agent_analysis/command.py
quickhooks/agent_analysis/context_manager.py
quickhooks/agent_analysis/types.py
quickhooks/agent_os/__init__.py
quickhooks/agent_os/executor.py
quickhooks/agent_os/hooks.py
quickhooks/agent_os/instruction_parser.py
quickhooks/agent_os/workflow_manager.py
quickhooks/claude_code/__init__.py
quickhooks/claude_code/manager.py
quickhooks/claude_code/models.py
quickhooks/cli/__init__.py
quickhooks/cli/agent_os.py
quickhooks/cli/create.py
quickhooks/cli/deploy.py
quickhooks/cli/features.py
quickhooks/cli/global_hooks.py
quickhooks/cli/install.py
quickhooks/cli/main.py
quickhooks/cli/scaffold.py
quickhooks/cli/settings.py
quickhooks/cli/smart.py
quickhooks/core/__init__.py
quickhooks/core/processor.py
quickhooks/db/__init__.py
quickhooks/db/indexer.py
quickhooks/db/manager.py
quickhooks/db/models.py
quickhooks/hooks/__init__.py
quickhooks/hooks/base.py
quickhooks/hooks/parallel.py
quickhooks/schema/__init__.py
quickhooks/schema/claude_settings_schema.json
quickhooks/schema/models.py
quickhooks/schema/validator.py
quickhooks/utils/__init__.py
quickhooks/utils/jinja_utils.py
quickhooks/visualization/__init__.py
quickhooks/visualization/mermaid_generator.py
quickhooks-0.2.0.dist-info/METADATA
quickhooks-0.2.0.dist-info/WHEEL
quickhooks-0.2.0.dist-info/entry_points.txt
quickhooks-0.2.0.dist-info/RECORD
