Metadata-Version: 2.4
Name: quickhooks
Version: 0.2.0
Summary: A streamlined TDD framework for Claude Code hooks with real-time feedback
Author-email: Kevin Hill <kivo360@gmail.com>
License: MIT
Classifier: Development Status :: 3 - Alpha
Classifier: Intended Audience :: Developers
Classifier: License :: OSI Approved :: MIT License
Classifier: Programming Language :: Python :: 3.12
Classifier: Programming Language :: Python :: 3.13
Classifier: Typing :: Typed
Requires-Python: >=3.12
Requires-Dist: chromadb>=0.4.0
Requires-Dist: groq>=0.13.0
Requires-Dist: ipython>=9.4.0
Requires-Dist: jinja2>=3.1.0
Requires-Dist: jsonschema>=4.25.0
Requires-Dist: lancedb>=0.24.2
Requires-Dist: mermaid-py>=0.8.0
Requires-Dist: openai>=1.97.1
Requires-Dist: pydantic-ai-slim[openai]>=0.0.49
Requires-Dist: pydantic-settings>=2.10.1
Requires-Dist: pydantic>=2.5.0
Requires-Dist: rich>=13.7.0
Requires-Dist: sentence-transformers>=2.2.0
Requires-Dist: typer[all]>=0.9.0
Requires-Dist: watchfiles>=0.20.0
Provides-Extra: agent-os
Requires-Dist: psutil>=5.9.0; extra == 'agent-os'
Provides-Extra: agents
Requires-Dist: anthropic>=0.18.0; extra == 'agents'
Requires-Dist: groq>=0.4.0; extra == 'agents'
Requires-Dist: openai>=1.0.0; extra == 'agents'
Requires-Dist: tiktoken>=0.5.0; extra == 'agents'
Provides-Extra: ai
Requires-Dist: lancedb>=0.8.0; extra == 'ai'
Requires-Dist: sentence-transformers>=2.2.0; extra == 'ai'
Requires-Dist: torch>=2.0.0; extra == 'ai'
Requires-Dist: transformers>=4.30.0; extra == 'ai'
Provides-Extra: all
Requires-Dist: aiocache>=0.12.0; extra == 'all'
Requires-Dist: anthropic>=0.18.0; extra == 'all'
Requires-Dist: azure-storage-blob>=12.17.0; extra == 'all'
Requires-Dist: black>=23.0.0; extra == 'all'
Requires-Dist: boto3>=1.28.0; extra == 'all'
Requires-Dist: celery>=5.3.0; extra == 'all'
Requires-Dist: cookiecutter>=2.1.0; extra == 'all'
Requires-Dist: cryptography>=41.0.0; extra == 'all'
Requires-Dist: duckdb>=0.9.0; extra == 'all'
Requires-Dist: fastapi>=0.100.0; extra == 'all'
Requires-Dist: google-cloud-storage>=2.10.0; extra == 'all'
Requires-Dist: groq>=0.4.0; extra == 'all'
Requires-Dist: isort>=5.12.0; extra == 'all'
Requires-Dist: lancedb>=0.8.0; extra == 'all'
Requires-Dist: lancedb[fts]>=0.8.0; extra == 'all'
Requires-Dist: ldap3>=2.9.0; extra == 'all'
Requires-Dist: mypy>=1.8.0; extra == 'all'
Requires-Dist: openai>=1.0.0; extra == 'all'
Requires-Dist: pandas>=2.0.0; extra == 'all'
Requires-Dist: plotly>=5.15.0; extra == 'all'
Requires-Dist: polars>=0.20.0; extra == 'all'
Requires-Dist: pre-commit>=3.0.0; extra == 'all'
Requires-Dist: prometheus-client>=0.17.0; extra == 'all'
Requires-Dist: psutil>=5.9.0; extra == 'all'
Requires-Dist: pyarrow>=12.0.0; extra == 'all'
Requires-Dist: pyjwt>=2.8.0; extra == 'all'
Requires-Dist: pytest-asyncio>=0.23.0; extra == 'all'
Requires-Dist: pytest-cov>=4.1.0; extra == 'all'
Requires-Dist: pytest-timeout>=2.2.0; extra == 'all'
Requires-Dist: pytest>=7.4.0; extra == 'all'
Requires-Dist: redis>=4.6.0; extra == 'all'
Requires-Dist: rich>=13.7.0; extra == 'all'
Requires-Dist: ruff>=0.1.9; extra == 'all'
Requires-Dist: sentence-transformers>=2.2.0; extra == 'all'
Requires-Dist: streamlit>=1.25.0; extra == 'all'
Requires-Dist: tantivy>=0.21.0; extra == 'all'
Requires-Dist: tiktoken>=0.5.0; extra == 'all'
Requires-Dist: torch>=2.0.0; extra == 'all'
Requires-Dist: transformers>=4.30.0; extra == 'all'
Requires-Dist: uvicorn>=0.23.0; extra == 'all'
Requires-Dist: websockets>=11.0.0; extra == 'all'
Provides-Extra: analytics
Requires-Dist: duckdb>=0.9.0; extra == 'analytics'
Requires-Dist: pandas>=2.0.0; extra == 'analytics'
Requires-Dist: plotly>=5.15.0; extra == 'analytics'
Requires-Dist: polars>=0.20.0; extra == 'analytics'
Requires-Dist: pyarrow>=12.0.0; extra == 'analytics'
Provides-Extra: cloud
Requires-Dist: azure-storage-blob>=12.17.0; extra == 'cloud'
Requires-Dist: boto3>=1.28.0; extra == 'cloud'
Requires-Dist: celery>=5.3.0; extra == 'cloud'
Requires-Dist: google-cloud-storage>=2.10.0; extra == 'cloud'
Requires-Dist: redis>=4.6.0; extra == 'cloud'
Provides-Extra: dev
Requires-Dist: mypy>=1.8.0; extra == 'dev'
Requires-Dist: pre-commit>=3.0.0; extra == 'dev'
Requires-Dist: pytest-asyncio>=0.23.0; extra == 'dev'
Requires-Dist: pytest-cov>=4.1.0; extra == 'dev'
Requires-Dist: pytest-timeout>=2.2.0; extra == 'dev'
Requires-Dist: pytest>=7.4.0; extra == 'dev'
Requires-Dist: rich>=13.7.0; extra == 'dev'
Requires-Dist: ruff>=0.1.9; extra == 'dev'
Provides-Extra: enterprise
Requires-Dist: cryptography>=41.0.0; extra == 'enterprise'
Requires-Dist: ldap3>=2.9.0; extra == 'enterprise'
Requires-Dist: prometheus-client>=0.17.0; extra == 'enterprise'
Requires-Dist: pyjwt>=2.8.0; extra == 'enterprise'
Provides-Extra: enterprise-full
Requires-Dist: aiocache>=0.12.0; extra == 'enterprise-full'
Requires-Dist: anthropic>=0.18.0; extra == 'enterprise-full'
Requires-Dist: azure-storage-blob>=12.17.0; extra == 'enterprise-full'
Requires-Dist: black>=23.0.0; extra == 'enterprise-full'
Requires-Dist: boto3>=1.28.0; extra == 'enterprise-full'
Requires-Dist: celery>=5.3.0; extra == 'enterprise-full'
Requires-Dist: cookiecutter>=2.1.0; extra == 'enterprise-full'
Requires-Dist: cryptography>=41.0.0; extra == 'enterprise-full'
Requires-Dist: duckdb>=0.9.0; extra == 'enterprise-full'
Requires-Dist: fastapi>=0.100.0; extra == 'enterprise-full'
Requires-Dist: google-cloud-storage>=2.10.0; extra == 'enterprise-full'
Requires-Dist: groq>=0.4.0; extra == 'enterprise-full'
Requires-Dist: isort>=5.12.0; extra == 'enterprise-full'
Requires-Dist: lancedb>=0.8.0; extra == 'enterprise-full'
Requires-Dist: lancedb[fts]>=0.8.0; extra == 'enterprise-full'
Requires-Dist: ldap3>=2.9.0; extra == 'enterprise-full'
Requires-Dist: mypy>=1.8.0; extra == 'enterprise-full'
Requires-Dist: openai>=1.0.0; extra == 'enterprise-full'
Requires-Dist: pandas>=2.0.0; extra == 'enterprise-full'
Requires-Dist: plotly>=5.15.0; extra == 'enterprise-full'
Requires-Dist: polars>=0.20.0; extra == 'enterprise-full'
Requires-Dist: pre-commit>=3.0.0; extra == 'enterprise-full'
Requires-Dist: prometheus-client>=0.17.0; extra == 'enterprise-full'
Requires-Dist: psutil>=5.9.0; extra == 'enterprise-full'
Requires-Dist: pyarrow>=12.0.0; extra == 'enterprise-full'
Requires-Dist: pyjwt>=2.8.0; extra == 'enterprise-full'
Requires-Dist: pytest-asyncio>=0.23.0; extra == 'enterprise-full'
Requires-Dist: pytest-cov>=4.1.0; extra == 'enterprise-full'
Requires-Dist: pytest-timeout>=2.2.0; extra == 'enterprise-full'
Requires-Dist: pytest>=7.4.0; extra == 'enterprise-full'
Requires-Dist: redis>=4.6.0; extra == 'enterprise-full'
Requires-Dist: rich>=13.7.0; extra == 'enterprise-full'
Requires-Dist: ruff>=0.1.9; extra == 'enterprise-full'
Requires-Dist: sentence-transformers>=2.2.0; extra == 'enterprise-full'
Requires-Dist: streamlit>=1.25.0; extra == 'enterprise-full'
Requires-Dist: tantivy>=0.21.0; extra == 'enterprise-full'
Requires-Dist: tiktoken>=0.5.0; extra == 'enterprise-full'
Requires-Dist: torch>=2.0.0; extra == 'enterprise-full'
Requires-Dist: transformers>=4.30.0; extra == 'enterprise-full'
Requires-Dist: uvicorn>=0.23.0; extra == 'enterprise-full'
Requires-Dist: websockets>=11.0.0; extra == 'enterprise-full'
Provides-Extra: essential
Requires-Dist: lancedb>=0.8.0; extra == 'essential'
Requires-Dist: lancedb[fts]>=0.8.0; extra == 'essential'
Requires-Dist: mypy>=1.8.0; extra == 'essential'
Requires-Dist: pre-commit>=3.0.0; extra == 'essential'
Requires-Dist: pytest-asyncio>=0.23.0; extra == 'essential'
Requires-Dist: pytest-cov>=4.1.0; extra == 'essential'
Requires-Dist: pytest-timeout>=2.2.0; extra == 'essential'
Requires-Dist: pytest>=7.4.0; extra == 'essential'
Requires-Dist: rich>=13.7.0; extra == 'essential'
Requires-Dist: ruff>=0.1.9; extra == 'essential'
Requires-Dist: sentence-transformers>=2.2.0; extra == 'essential'
Requires-Dist: tantivy>=0.21.0; extra == 'essential'
Requires-Dist: torch>=2.0.0; extra == 'essential'
Requires-Dist: transformers>=4.30.0; extra == 'essential'
Provides-Extra: performance
Requires-Dist: aiocache>=0.12.0; extra == 'performance'
Requires-Dist: psutil>=5.9.0; extra == 'performance'
Requires-Dist: redis>=4.6.0; extra == 'performance'
Provides-Extra: pro
Requires-Dist: anthropic>=0.18.0; extra == 'pro'
Requires-Dist: black>=23.0.0; extra == 'pro'
Requires-Dist: cookiecutter>=2.1.0; extra == 'pro'
Requires-Dist: duckdb>=0.9.0; extra == 'pro'
Requires-Dist: groq>=0.4.0; extra == 'pro'
Requires-Dist: isort>=5.12.0; extra == 'pro'
Requires-Dist: lancedb>=0.8.0; extra == 'pro'
Requires-Dist: lancedb[fts]>=0.8.0; extra == 'pro'
Requires-Dist: mypy>=1.8.0; extra == 'pro'
Requires-Dist: openai>=1.0.0; extra == 'pro'
Requires-Dist: pandas>=2.0.0; extra == 'pro'
Requires-Dist: plotly>=5.15.0; extra == 'pro'
Requires-Dist: polars>=0.20.0; extra == 'pro'
Requires-Dist: pre-commit>=3.0.0; extra == 'pro'
Requires-Dist: psutil>=5.9.0; extra == 'pro'
Requires-Dist: pyarrow>=12.0.0; extra == 'pro'
Requires-Dist: pytest-asyncio>=0.23.0; extra == 'pro'
Requires-Dist: pytest-cov>=4.1.0; extra == 'pro'
Requires-Dist: pytest-timeout>=2.2.0; extra == 'pro'
Requires-Dist: pytest>=7.4.0; extra == 'pro'
Requires-Dist: rich>=13.7.0; extra == 'pro'
Requires-Dist: ruff>=0.1.9; extra == 'pro'
Requires-Dist: sentence-transformers>=2.2.0; extra == 'pro'
Requires-Dist: tantivy>=0.21.0; extra == 'pro'
Requires-Dist: tiktoken>=0.5.0; extra == 'pro'
Requires-Dist: torch>=2.0.0; extra == 'pro'
Requires-Dist: transformers>=4.30.0; extra == 'pro'
Provides-Extra: scaffold
Requires-Dist: black>=23.0.0; extra == 'scaffold'
Requires-Dist: cookiecutter>=2.1.0; extra == 'scaffold'
Requires-Dist: isort>=5.12.0; extra == 'scaffold'
Provides-Extra: search
Requires-Dist: lancedb[fts]>=0.8.0; extra == 'search'
Requires-Dist: tantivy>=0.21.0; extra == 'search'
Provides-Extra: web
Requires-Dist: fastapi>=0.100.0; extra == 'web'
Requires-Dist: streamlit>=1.25.0; extra == 'web'
Requires-Dist: uvicorn>=0.23.0; extra == 'web'
Requires-Dist: websockets>=11.0.0; extra == 'web'
